Metadata-Version: 2.4
Name: frame-alignment-checks
Version: 0.0.73
Summary: Library for determining whether a RNA splicing predictor is using frame alignment information
Home-page: https://github.com/kavigupta/frame-alignment-checks
Author: Kavi Gupta
Author-email: frame-alignment-checks@kavigupta.org
Project-URL: Documentation, https://frame-alignment-checks.readthedocs.io/en/latest/#
Classifier: Programming Language :: Python :: 3.9
Classifier: Programming Language :: Python :: 3.10
Classifier: Programming Language :: Python :: 3.11
Classifier: Programming Language :: Python :: 3.12
Classifier: Operating System :: OS Independent
Requires-Python: >=3.9
Requires-Dist: numpy
Requires-Dist: frozendict>=2.4.6
Requires-Dist: permacache>=3.12.0
Requires-Dist: tqdm>4.0.0
Requires-Dist: render-psam>=1.0.1
Requires-Dist: run-batched>=1.0.2
Requires-Dist: matplotlib_venn>=1.1.1
Requires-Dist: dconstruct>=1.0.0
Dynamic: author-email
Dynamic: classifier
Dynamic: description
Dynamic: description-content-type
Dynamic: home-page
Dynamic: project-url
Dynamic: requires-dist
Dynamic: requires-python
Dynamic: summary
